{
    "name": "Wizard",
    "class_features": {
        "hit_points": {
            "hit_dice": 6,
            "average_per_level": 4
        },
        "proficiencies": {
            "armor": [],
            "weapons": ["dagger", "dart", "sling", "quarterstaff", "light crossbow"],
            "tools": [],
            "savingThrows": ["intelligence", "wisdom"],
            "skills": ["arcana", "history", "insight", "investigation", "medicine", "religion"],
            "skillsChoose": 2,
            "hasSpellcasting": true,
            "hasRage": false,
            "hasKi": false,
            "hasSneakAttack": false,
            "hasSorceryPoints": false,
            "hasInvocations": false
        },
        "equipment": {
            "items": [
                {"choices": ["quarterstaff", "dagger"]},
                {"choices": ["component pouch", "arcane focus"]},
                {"choices": ["scholar’s pack", "explorer’s pack"]},
                {"fixed": ["spellbook"]}
            ]
        }
    },
    "progression": [
        {"lv": 1, "features": ["Spellcasting", "Arcane Recovery"]},
        {"lv": 2, "features": ["Arcane Tradition"]},
        {"lv": 3, "features": ["-"]},
        {"lv": 4, "features": ["Ability Score Improvement"]},
        {"lv": 5, "features": ["-"]},
        {"lv": 6, "features": ["Arcane Tradition Feature"]},
        {"lv": 7, "features": ["-"]},
        {"lv": 8, "features": ["Ability Score Improvement"]},
        {"lv": 9, "features": ["-"]},
        {"lv": 10, "features": ["Arcane Tradition Feature"]},
        {"lv": 11, "features": ["-"]},
        {"lv": 12, "features": ["Ability Score Improvement"]},
        {"lv": 13, "features": ["-"]},
        {"lv": 14, "features": ["Arcane Tradition Feature"]},
        {"lv": 15, "features": ["-"]},
        {"lv": 16, "features": ["Ability Score Improvement"]},
        {"lv": 17, "features": ["Spell Mastery"]},
        {"lv": 18, "features": ["Ability Score Improvement"]},
        {"lv": 19, "features": ["Signature Spell"]},
        {"lv": 20, "features": ["-"]}
    ]
}